Workbook

Sheet Simulador
B2: Simulador de Investimentos em Fundos Imobiliários
B6: Entradas da simulação | F6: Resultados
B7: Salário mensal | D7: 2500 | F7: Total investido | H7: =D11*D12*12 -> 72000
B8: Percentual sugerido para investir | D8: 0.3 | F8: Patrimônio acumulado | H8: =IF(D13=0,D11*D12*12,D11*((1+D13)^(D12*12)-1)/D13) -> 138023.21
B9: Aporte mensal sugerido | D9: =D7*D8 -> 750 | F9: Rendimentos acumulados | H9: =H8-H7 -> 66023.214
F10: Dividendos mensais | H10: =H8*D14 -> 828.13928
B11: Aporte mensal escolhido | D11: 600 | F11: Ganho sobre os aportes | H11: =IF(H7=0,"",H9/H7) -> 0.91698908
B12: Prazo do investimento (anos) | D12: 10
B13: Taxa de rendimento mensal | D13: 0.01
B14: Taxa mensal de dividendos | D14: 0.006
B15: Perfil de investidor | D15: Moderado
B17: Cenários por prazo
B18: Prazo (anos) | C18: Meses | D18: Total investido | E18: Patrimônio acumulado | F18: Dividendos mensais
B19: 2 | C19: =B19*12 -> 24 | D19: =$D$11*C19 -> 14400 | E19: =IF($D$13=0,$D$11*C19,$D$11*((1+$D$13)^C19-1)/$D$13) -> 16184.079 | F19: =E19*$D$14 -> 97.104473
B20: 5 | C20: =B20*12 -> 60 | D20: =$D$11*C20 -> 36000 | E20: =IF($D$13=0,$D$11*C20,$D$11*((1+$D$13)^C20-1)/$D$13) -> 49001.802 | F20: =E20*$D$14 -> 294.01081
B21: 10 | C21: =B21*12 -> 120 | D21: =$D$11*C21 -> 72000 | E21: =IF($D$13=0,$D$11*C21,$D$11*((1+$D$13)^C21-1)/$D$13) -> 138023.21 | F21: =E21*$D$14 -> 828.13928
B22: 20 | C22: =B22*12 -> 240 | D22: =$D$11*C22 -> 144000 | E22: =IF($D$13=0,$D$11*C22,$D$11*((1+$D$13)^C22-1)/$D$13) -> 593553.22 | F22: =E22*$D$14 -> 3561.3193
B23: 30 | C23: =B23*12 -> 360 | D23: =$D$11*C23 -> 216000 | E23: =IF($D$13=0,$D$11*C23,$D$11*((1+$D$13)^C23-1)/$D$13) -> 2096978.5 | F23: =E23*$D$14 -> 12581.871
B27: Distribuição sugerida por perfil
B28: Tipo de FII | C28: Percentual | D28: Valor mensal
B29: Papel | C29: =INDEX(Perfis!$E$3:$E$20,MATCH($D$15&"-"&B29,Perfis!$B$3:$B$20,0)) -> 0.32 | D29: =C29*$D$11 -> 192
B30: Tijolo | C30: =INDEX(Perfis!$E$3:$E$20,MATCH($D$15&"-"&B30,Perfis!$B$3:$B$20,0)) -> 0.35 | D30: =C30*$D$11 -> 210
B31: Híbridos | C31: =INDEX(Perfis!$E$3:$E$20,MATCH($D$15&"-"&B31,Perfis!$B$3:$B$20,0)) -> 0.08 | D31: =C31*$D$11 -> 48
B32: FOFs | C32: =INDEX(Perfis!$E$3:$E$20,MATCH($D$15&"-"&B32,Perfis!$B$3:$B$20,0)) -> 0.05 | D32: =C32*$D$11 -> 30
B33: Desenvolvimento | C33: =INDEX(Perfis!$E$3:$E$20,MATCH($D$15&"-"&B33,Perfis!$B$3:$B$20,0)) -> 0.1 | D33: =C33*$D$11 -> 60
B34: Hotelaria | C34: =INDEX(Perfis!$E$3:$E$20,MATCH($D$15&"-"&B34,Perfis!$B$3:$B$20,0)) -> 0.1 | D34: =C34*$D$11 -> 60
B35: Total | C35: =SUM(C29:C34) -> 1 | D35: =SUM(D29:D34) -> 600

Sheet Perfis
B2: Chave | C2: Perfil | D2: Tipo de FII | E2: Percentual | G2: Fonte e premissas
B3: =C3&"-"&D3 -> Conservador-Papel | C3: Conservador | D3: Papel | E3: 0.3 | G3: Modelo de referência | H3: Desafio DIO: Simulador de Investimentos em FIIs
B4: =C4&"-"&D4 -> Conservador-Tijolo | C4: Conservador | D4: Tijolo | E4: 0.5 | G4: Taxas | H4: Hipóteses editáveis para fins educacionais
B5: =C5&"-"&D5 -> Conservador-Híbridos | C5: Conservador | D5: Híbridos | E5: 0.1 | G5: Perfis | H5: Percentuais inspirados no arquivo resolvido disponibilizado no desafio
B6: =C6&"-"&D6 -> Conservador-FOFs | C6: Conservador | D6: FOFs | E6: 0.1 | G6: Retorno | H6: Não representa promessa ou recomendação de investimento
B7: =C7&"-"&D7 -> Conservador-Desenvolvimento | C7: Conservador | D7: Desenvolvimento | E7: 0
B8: =C8&"-"&D8 -> Conservador-Hotelaria | C8: Conservador | D8: Hotelaria | E8: 0
B9: =C9&"-"&D9 -> Moderado-Papel | C9: Moderado | D9: Papel | E9: 0.32
B10: =C10&"-"&D10 -> Moderado-Tijolo | C10: Moderado | D10: Tijolo | E10: 0.35
B11: =C11&"-"&D11 -> Moderado-Híbridos | C11: Moderado | D11: Híbridos | E11: 0.08
B12: =C12&"-"&D12 -> Moderado-FOFs | C12: Moderado | D12: FOFs | E12: 0.05
B13: =C13&"-"&D13 -> Moderado-Desenvolvimento | C13: Moderado | D13: Desenvolvimento | E13: 0.1
B14: =C14&"-"&D14 -> Moderado-Hotelaria | C14: Moderado | D14: Hotelaria | E14: 0.1
B15: =C15&"-"&D15 -> Agressivo-Papel | C15: Agressivo | D15: Papel | E15: 0.5
B16: =C16&"-"&D16 -> Agressivo-Tijolo | C16: Agressivo | D16: Tijolo | E16: 0.1
B17: =C17&"-"&D17 -> Agressivo-Híbridos | C17: Agressivo | D17: Híbridos | E17: 0.05
B18: =C18&"-"&D18 -> Agressivo-FOFs | C18: Agressivo | D18: FOFs | E18: 0.05
... B20: =C20&"-"&D20 -> Agressivo-Hotelaria | C20: Agressivo | D20: Hotelaria | E20: 0.1
